{
	"name": "zoneLimiter",
	"plugin-id": "Sprite",
	"sid": 875796887405404,
	"isGlobal": false,
	"instanceVariables": [],
	"behaviorTypes": [
		{
			"behaviorId": "solid",
			"name": "Solid",
			"sid": 515330782688650
		},
		{
			"behaviorId": "Pin",
			"name": "Pin",
			"sid": 190409476242206
		},
		{
			"behaviorId": "Sin",
			"name": "Sine",
			"sid": 580141415045579
		},
		{
			"behaviorId": "Sin",
			"name": "Sine2",
			"sid": 341475940602126
		}
	],
	"effectTypes": [],
	"animations": {
		"items": [
			{
				"frames": [
					{
						"width": 250,
						"height": 250,
						"originX": 0.5,
						"originY": 0.5,
						"originalSource": "",
						"exportFormat": "png",
						"exportQuality": 0.8,
						"imageSpriteId": 6898303,
						"useCollisionPoly": true,
						"duration": 1
					}
				],
				"sid": 634159417233006,
				"name": "Animation 1",
				"isLooping": false,
				"isPingPong": false,
				"repeatCount": 1,
				"repeatTo": 0,
				"speed": 5
			}
		],
		"subfolders": []
	}
}